{"id":21595,"bairro":"Abranches","cidade":"Curitiba","slug_cidade":"curitiba","estado":"Paran\u00e1","uf":"PR","slug_uf":"pr","faixa_cep_inicial":"82130010","faixa_cep_final":"82220670","slug":"abranches","meta_titulo_google":"Abranches Cep ruas do bairro Abranches curitiba PR","meta_descricao_google":"Abranches curitiba cep Abranches curitiba PR \u2714\ufe0f faixa de cep 82130010 - 82220670 \u2714\ufe0f consulta as ruas do bairro Abranches cep","numero_enderecos":133,"data_hora_criacao":"2023-05-16 18:45:03","data_hora_atualizacao":"2024-05-19 00:21:00","total_comentarios":0,"media_avaliacao":null}