{"id":14207,"bairro":"Adelmol\u00e2ndia","cidade":"Sabar\u00e1","slug_cidade":"sabara","estado":"Minas Gerais","uf":"MG","slug_uf":"mg","faixa_cep_inicial":"34525402","faixa_cep_final":"34525600","slug":"adelmolandia","meta_titulo_google":"Adelmol\u00e2ndia Cep ruas Adelmol\u00e2ndia sabar\u00e1 MG","meta_descricao_google":"Adelmol\u00e2ndia sabar\u00e1 cep Adelmol\u00e2ndia sabar\u00e1 MG \u2714\ufe0f faixa de cep 34525402 - 34525600 \u2714\ufe0f veja as ruas do bairro Adelmol\u00e2ndia","numero_enderecos":36,"data_hora_criacao":"2023-05-14 13:54:03","data_hora_atualizacao":"2024-05-19 00:21:00","total_comentarios":0,"media_avaliacao":null}