{"id":15950,"bairro":"Altos da Mata","cidade":"Campo Grande","slug_cidade":"campo-grande","estado":"Mato Grosso do Sul","uf":"MS","slug_uf":"ms","faixa_cep_inicial":"79040161","faixa_cep_final":"79040167","slug":"altos-da-mata","meta_titulo_google":"Altos da mata Cep ruas Altos da mata campo grande MS","meta_descricao_google":"Altos da mata campo grande cep Altos da mata campo grande MS \u2714\ufe0f faixa de cep 79040161 - 79040167 \u2714\ufe0f veja as ruas do bairro Altos da mata","numero_enderecos":7,"data_hora_criacao":"2023-05-14 22:28:28","data_hora_atualizacao":"2024-05-19 00:21:00","total_comentarios":0,"media_avaliacao":null}