{"id":21323,"bairro":"Alto Faraday","cidade":"Capanema","slug_cidade":"capanema","estado":"Paran\u00e1","uf":"PR","slug_uf":"pr","faixa_cep_inicial":"85760000","faixa_cep_final":"85760000","slug":"alto-faraday","meta_titulo_google":"Alto faraday Cep ruas Alto faraday capanema PR","meta_descricao_google":"Alto faraday capanema cep Alto faraday capanema PR \u2714\ufe0f busca cep 85760000 \u00fanico \u2714\ufe0f ruas do bairro Alto faraday capanema","numero_enderecos":0,"data_hora_criacao":"2023-05-16 17:25:32","data_hora_atualizacao":"2024-05-19 00:21:00","total_comentarios":0,"media_avaliacao":null}