{"id":7553,"bairro":"\u00c1rea Rural de Valpara\u00edso de Goi\u00e1s","cidade":"Valpara\u00edso de Goi\u00e1s","slug_cidade":"valparaiso-de-goias","estado":"Goi\u00e1s","uf":"GO","slug_uf":"go","faixa_cep_inicial":"72879899","faixa_cep_final":"72879899","slug":"area-rural-de-valparaiso-de-goias","meta_titulo_google":"\u00e1rea rural de valpara\u00edso de goi\u00e1s CEP valpara\u00edso de GO","meta_descricao_google":"\u00e1rea rural de valpara\u00edso de goi\u00e1s valpara\u00edso de cep \u00e1rea rural de valpara\u00edso de goi\u00e1s valpara\u00edso de GO busca cep 72879899 \u00fanico","numero_enderecos":0,"data_hora_criacao":"2023-05-13 05:35:04","data_hora_atualizacao":"2024-05-19 00:21:00","total_comentarios":0,"media_avaliacao":null}