{"id":27151,"bairro":"\u00c1rea Rural de Porto Velho","cidade":"Porto Velho","slug_cidade":"porto-velho","estado":"Rond\u00f4nia","uf":"RO","slug_uf":"ro","faixa_cep_inicial":"76834899","faixa_cep_final":"76834899","slug":"area-rural-de-porto-velho","meta_titulo_google":"\u00e1rea rural de porto velho CEP bairro porto velho RO","meta_descricao_google":"\u00e1rea rural de porto velho porto velho cep \u00e1rea rural de porto velho porto velho RO \u2714\ufe0f busca cep 76834899 \u00fanico ruas do bairro","numero_enderecos":0,"data_hora_criacao":"2023-05-19 04:47:04","data_hora_atualizacao":"2024-05-19 00:21:00","total_comentarios":0,"media_avaliacao":null}