{"id":39412,"bairro":"\u00c1rea Rural de Macucos","cidade":"Getulina","slug_cidade":"getulina","estado":"S\u00e3o Paulo","uf":"SP","slug_uf":"sp","faixa_cep_inicial":"16459899","faixa_cep_final":"16459899","slug":"area-rural-de-macucos","meta_titulo_google":"\u00e1rea rural de macucos Cep do bairro em getulina SP","meta_descricao_google":"\u00e1rea rural de macucos getulina cep \u00e1rea rural de macucos getulina SP \u2714\ufe0f busca cep 16459899 \u00fanico bairro \u00e1rea rural de macucos","numero_enderecos":0,"data_hora_criacao":"2023-05-21 11:21:03","data_hora_atualizacao":"2024-05-19 00:21:00","total_comentarios":0,"media_avaliacao":null}