{"id":33903,"bairro":"Bairro dos Pires","cidade":"Atibaia","slug_cidade":"atibaia","estado":"S\u00e3o Paulo","uf":"SP","slug_uf":"sp","faixa_cep_inicial":"12953232","faixa_cep_final":"12953232","slug":"bairro-dos-pires","meta_titulo_google":"Bairro dos pires Cep Bairro dos pires atibaia SP","meta_descricao_google":"Bairro dos pires atibaia cep Bairro dos pires atibaia SP \u2714\ufe0f busca cep 12953232 \u00fanico \u2714\ufe0f veja ruas do bairro Bairro dos pires","numero_enderecos":0,"data_hora_criacao":"2023-05-20 10:11:44","data_hora_atualizacao":"2024-05-19 00:21:00","total_comentarios":0,"media_avaliacao":null}