{"id":25221,"bairro":"Belmonte","cidade":"Nova Igua\u00e7u","slug_cidade":"nova-iguacu","estado":"Rio de Janeiro","uf":"RJ","slug_uf":"rj","faixa_cep_inicial":"26250040","faixa_cep_final":"26250090","slug":"belmonte","meta_titulo_google":"Belmonte Cep ruas do bairro Belmonte nova igua\u00e7u RJ","meta_descricao_google":"Belmonte nova igua\u00e7u cep Belmonte nova igua\u00e7u RJ \u2714\ufe0f faixa de cep 26250040 - 26250090 \u2714\ufe0f consulta as ruas do bairro Belmonte cep","numero_enderecos":4,"data_hora_criacao":"2023-05-18 11:37:14","data_hora_atualizacao":"2024-05-19 00:21:00","total_comentarios":0,"media_avaliacao":null}