{"id":3979,"bairro":"Bicanga","cidade":"Serra","slug_cidade":"serra","estado":"Esp\u00edrito Santo","uf":"ES","slug_uf":"es","faixa_cep_inicial":"29164731","faixa_cep_final":"29164817","slug":"bicanga","meta_titulo_google":"Bicanga Cep ruas do bairro Bicanga serra ES","meta_descricao_google":"Bicanga serra cep Bicanga serra ES \u2714\ufe0f faixa de cep 29164731 - 29164817 \u2714\ufe0f consulta as ruas do bairro Bicanga cep","numero_enderecos":55,"data_hora_criacao":"2023-05-12 00:05:35","data_hora_atualizacao":"2024-05-19 00:21:00","total_comentarios":0,"media_avaliacao":null}