{"id":14544,"bairro":"Biguatinga","cidade":"S\u00e3o Pedro da Uni\u00e3o","slug_cidade":"sao-pedro-da-uniao","estado":"Minas Gerais","uf":"MG","slug_uf":"mg","faixa_cep_inicial":"37855000","faixa_cep_final":"37855000","slug":"biguatinga","meta_titulo_google":"Biguatinga Cep ruas do bairro Biguatinga s\u00e3o pedro da MG","meta_descricao_google":"Biguatinga s\u00e3o pedro da cep Biguatinga s\u00e3o pedro da MG \u2714\ufe0f busca cep 37855000 \u00fanico \u2714\ufe0f veja endere\u00e7os do bairro Biguatinga s\u00e3o pedro da","numero_enderecos":0,"data_hora_criacao":"2023-05-14 15:32:13","data_hora_atualizacao":"2024-05-19 00:21:00","total_comentarios":0,"media_avaliacao":null}