{"id":4118,"bairro":"Boa Esperan\u00e7a","cidade":"Viana","slug_cidade":"viana","estado":"Esp\u00edrito Santo","uf":"ES","slug_uf":"es","faixa_cep_inicial":"29130300","faixa_cep_final":"29130339","slug":"boa-esperanca","meta_titulo_google":"Boa esperan\u00e7a Cep ruas Boa esperan\u00e7a viana ES","meta_descricao_google":"Boa esperan\u00e7a viana cep Boa esperan\u00e7a viana ES \u2714\ufe0f faixa de cep 29130300 - 29130339 \u2714\ufe0f veja as ruas do bairro Boa esperan\u00e7a","numero_enderecos":14,"data_hora_criacao":"2023-05-12 00:46:06","data_hora_atualizacao":"2024-05-19 00:21:00","total_comentarios":0,"media_avaliacao":null}