{"id":31558,"bairro":"Boehmerwald","cidade":"Joinville","slug_cidade":"joinville","estado":"Santa Catarina","uf":"SC","slug_uf":"sc","faixa_cep_inicial":"89232110","faixa_cep_final":"89235570","slug":"boehmerwald","meta_titulo_google":"Boehmerwald Cep ruas Boehmerwald joinville SC","meta_descricao_google":"Boehmerwald joinville cep Boehmerwald joinville SC \u2714\ufe0f faixa de cep 89232110 - 89235570 \u2714\ufe0f veja as ruas do bairro Boehmerwald","numero_enderecos":143,"data_hora_criacao":"2023-05-20 00:08:44","data_hora_atualizacao":"2024-05-19 00:21:00","total_comentarios":0,"media_avaliacao":null}