{"id":9213,"bairro":"Brodoski","cidade":"Betim","slug_cidade":"betim","estado":"Minas Gerais","uf":"MG","slug_uf":"mg","faixa_cep_inicial":"32616500","faixa_cep_final":"32616540","slug":"brodoski","meta_titulo_google":"Brodoski Cep ruas do bairro Brodoski betim MG","meta_descricao_google":"Brodoski betim cep Brodoski betim MG \u2714\ufe0f faixa de cep 32616500 - 32616540 \u2714\ufe0f consulta as ruas do bairro Brodoski cep","numero_enderecos":5,"data_hora_criacao":"2023-05-13 13:49:45","data_hora_atualizacao":"2024-05-19 00:21:00","total_comentarios":0,"media_avaliacao":null}