{"id":9215,"bairro":"Calif\u00f3rnia","cidade":"Betim","slug_cidade":"betim","estado":"Minas Gerais","uf":"MG","slug_uf":"mg","faixa_cep_inicial":"32618400","faixa_cep_final":"32618540","slug":"california","meta_titulo_google":"Calif\u00f3rnia Cep ruas do bairro Calif\u00f3rnia betim MG","meta_descricao_google":"Calif\u00f3rnia betim cep Calif\u00f3rnia betim MG \u2714\ufe0f faixa de cep 32618400 - 32618540 \u2714\ufe0f consulta as ruas do bairro Calif\u00f3rnia cep","numero_enderecos":12,"data_hora_criacao":"2023-05-13 13:50:21","data_hora_atualizacao":"2024-05-19 00:21:00","total_comentarios":0,"media_avaliacao":null}