{"id":31437,"bairro":"Carij\u00f3s","cidade":"Indaial","slug_cidade":"indaial","estado":"Santa Catarina","uf":"SC","slug_uf":"sc","faixa_cep_inicial":"89084000","faixa_cep_final":"89084397","slug":"carijos","meta_titulo_google":"Carij\u00f3s Cep ruas do bairro Carij\u00f3s indaial SC","meta_descricao_google":"Carij\u00f3s indaial cep Carij\u00f3s indaial SC \u2714\ufe0f faixa de cep 89084000 - 89084397 \u2714\ufe0f consulta as ruas do bairro Carij\u00f3s cep","numero_enderecos":73,"data_hora_criacao":"2023-05-19 23:38:28","data_hora_atualizacao":"2024-05-19 00:21:00","total_comentarios":0,"media_avaliacao":null}