{"id":43073,"bairro":"Centro","cidade":"Jo\u00e3o Ramalho","slug_cidade":"joao-ramalho","estado":"S\u00e3o Paulo","uf":"SP","slug_uf":"sp","faixa_cep_inicial":"19680001","faixa_cep_final":"19680970","slug":"centro","meta_titulo_google":"Centro Cep Centro jo\u00e3o ramalho SP veja as ruas do bairro","meta_descricao_google":"Centro jo\u00e3o ramalho cep Centro jo\u00e3o ramalho SP \u2714\ufe0f faixa de cep 19680001 - 19680970 \u2714\ufe0f veja as ruas do bairro Centro \u2714\ufe0f consulta endere\u00e7o","numero_enderecos":28,"data_hora_criacao":"2023-05-21 22:10:43","data_hora_atualizacao":"2024-05-19 00:21:00","total_comentarios":0,"media_avaliacao":null}