{"id":9613,"bairro":"Centro","cidade":"Cataguases","slug_cidade":"cataguases","estado":"Minas Gerais","uf":"MG","slug_uf":"mg","faixa_cep_inicial":"36770001","faixa_cep_final":"36774042","slug":"centro","meta_titulo_google":"Centro Cep Centro cataguases MG veja as ruas do bairro","meta_descricao_google":"Centro cataguases cep Centro cataguases MG \u2714\ufe0f faixa de cep 36770001 - 36774042 \u2714\ufe0f veja as ruas do bairro Centro \u2714\ufe0f consulta endere\u00e7o","numero_enderecos":75,"data_hora_criacao":"2023-05-13 15:47:06","data_hora_atualizacao":"2024-05-19 00:21:00","total_comentarios":0,"media_avaliacao":null}