{"id":27050,"bairro":"Centro","cidade":"Campo Novo de Rond\u00f4nia","slug_cidade":"campo-novo-de-rondonia","estado":"Rond\u00f4nia","uf":"RO","slug_uf":"ro","faixa_cep_inicial":"76887000","faixa_cep_final":"76887000","slug":"centro","meta_titulo_google":"Centro Cep Centro campo novo de RO  veja as ruas do bairro","meta_descricao_google":"Centro campo novo de cep Centro campo novo de RO \u2714\ufe0f busca cep 76887000 \u00fanico \u2714\ufe0f ruas do bairro Centro campo novo de \u2714\ufe0f consulta 76887000","numero_enderecos":0,"data_hora_criacao":"2023-05-19 04:19:49","data_hora_atualizacao":"2024-05-19 00:21:00","total_comentarios":0,"media_avaliacao":null}