{"id":39481,"bairro":"Centro","cidade":"Guapiara","slug_cidade":"guapiara","estado":"S\u00e3o Paulo","uf":"SP","slug_uf":"sp","faixa_cep_inicial":"18310000","faixa_cep_final":"18310000","slug":"centro","meta_titulo_google":"Centro Cep Centro guapiara SP  veja as ruas do bairro","meta_descricao_google":"Centro guapiara cep Centro guapiara SP \u2714\ufe0f busca cep 18310000 \u00fanico \u2714\ufe0f ruas do bairro Centro guapiara \u2714\ufe0f consulta 18310000","numero_enderecos":0,"data_hora_criacao":"2023-05-21 11:32:33","data_hora_atualizacao":"2024-05-19 00:21:00","total_comentarios":0,"media_avaliacao":null}