{"id":27386,"bairro":"Centro","cidade":"Uiramut\u00e3","slug_cidade":"uiramuta","estado":"Roraima","uf":"RR","slug_uf":"rr","faixa_cep_inicial":"69358000","faixa_cep_final":"69358000","slug":"centro","meta_titulo_google":"Centro Cep Centro uiramut\u00e3 RR  veja as ruas do bairro","meta_descricao_google":"Centro uiramut\u00e3 cep Centro uiramut\u00e3 RR \u2714\ufe0f busca cep 69358000 \u00fanico \u2714\ufe0f ruas do bairro Centro uiramut\u00e3 \u2714\ufe0f consulta 69358000","numero_enderecos":0,"data_hora_criacao":"2023-05-19 07:20:12","data_hora_atualizacao":"2024-05-19 00:21:00","total_comentarios":0,"media_avaliacao":null}