{"id":16915,"bairro":"Centro","cidade":"Bom Jesus do Araguaia","slug_cidade":"bom-jesus-do-araguaia","estado":"Mato Grosso","uf":"MT","slug_uf":"mt","faixa_cep_inicial":"78678000","faixa_cep_final":"78678000","slug":"centro","meta_titulo_google":"Centro Cep Centro bom jesus do MT  veja as ruas do bairro","meta_descricao_google":"Centro bom jesus do cep Centro bom jesus do MT \u2714\ufe0f busca cep 78678000 \u00fanico \u2714\ufe0f ruas do bairro Centro bom jesus do \u2714\ufe0f consulta 78678000","numero_enderecos":0,"data_hora_criacao":"2023-05-15 17:33:51","data_hora_atualizacao":"2024-05-19 00:21:00","total_comentarios":0,"media_avaliacao":null}