{"id":21581,"bairro":"Centro","cidade":"Conselheiro Mairinck","slug_cidade":"conselheiro-mairinck","estado":"Paran\u00e1","uf":"PR","slug_uf":"pr","faixa_cep_inicial":"86480000","faixa_cep_final":"86480000","slug":"centro","meta_titulo_google":"Centro Cep Centro conselheiro PR  veja as ruas do bairro","meta_descricao_google":"Centro conselheiro cep Centro conselheiro PR \u2714\ufe0f busca cep 86480000 \u00fanico \u2714\ufe0f ruas do bairro Centro conselheiro \u2714\ufe0f consulta 86480000","numero_enderecos":0,"data_hora_criacao":"2023-05-16 18:41:08","data_hora_atualizacao":"2024-05-19 00:21:00","total_comentarios":0,"media_avaliacao":null}