{"id":16371,"bairro":"Centro","cidade":"Corguinho","slug_cidade":"corguinho","estado":"Mato Grosso do Sul","uf":"MS","slug_uf":"ms","faixa_cep_inicial":"79460000","faixa_cep_final":"79460000","slug":"centro","meta_titulo_google":"Centro Cep Centro corguinho MS  veja as ruas do bairro","meta_descricao_google":"Centro corguinho cep Centro corguinho MS \u2714\ufe0f busca cep 79460000 \u00fanico \u2714\ufe0f ruas do bairro Centro corguinho \u2714\ufe0f consulta 79460000","numero_enderecos":0,"data_hora_criacao":"2023-05-15 02:23:05","data_hora_atualizacao":"2024-05-19 00:21:00","total_comentarios":0,"media_avaliacao":null}