{"id":7067,"bairro":"C\u00e9u Azul","cidade":"Rio Verde","slug_cidade":"rio-verde","estado":"Goi\u00e1s","uf":"GO","slug_uf":"go","faixa_cep_inicial":"75910200","faixa_cep_final":"75910251","slug":"ceu-azul","meta_titulo_google":"C\u00e9u azul Cep ruas do bairro C\u00e9u azul rio verde GO","meta_descricao_google":"C\u00e9u azul rio verde cep C\u00e9u azul rio verde GO \u2714\ufe0f faixa de cep 75910200 - 75910251 \u2714\ufe0f consulta as ruas do bairro C\u00e9u azul cep","numero_enderecos":18,"data_hora_criacao":"2023-05-13 03:16:16","data_hora_atualizacao":"2024-05-19 00:21:00","total_comentarios":0,"media_avaliacao":null}