{"id":35449,"bairro":"Ch\u00e1cara de Recreio Jardim Alvorada","cidade":"Botucatu","slug_cidade":"botucatu","estado":"S\u00e3o Paulo","uf":"SP","slug_uf":"sp","faixa_cep_inicial":"18615502","faixa_cep_final":"18615522","slug":"chacara-de-recreio-jardim-alvorada","meta_titulo_google":"Ch\u00e1cara de recreio jardim alvorada CEP botucatu SP","meta_descricao_google":"Ch\u00e1cara de recreio jardim alvorada botucatu cep Ch\u00e1cara de recreio jardim alvorada botucatu SP cep 18615502 - 18615522","numero_enderecos":11,"data_hora_criacao":"2023-05-20 17:09:13","data_hora_atualizacao":"2024-05-19 00:21:00","total_comentarios":0,"media_avaliacao":null}