{"id":14631,"bairro":"Ch\u00e1cara Esplanada do Moinho","cidade":"Sete Lagoas","slug_cidade":"sete-lagoas","estado":"Minas Gerais","uf":"MG","slug_uf":"mg","faixa_cep_inicial":"35703520","faixa_cep_final":"35703530","slug":"chacara-esplanada-do-moinho","meta_titulo_google":"Ch\u00e1cara esplanada do moinho CEP bairro sete lagoas MG","meta_descricao_google":"Ch\u00e1cara esplanada do moinho sete lagoas cep Ch\u00e1cara esplanada do moinho sete lagoas MG \u2714\ufe0f veja faixa de cep 35703520 - 35703530","numero_enderecos":6,"data_hora_criacao":"2023-05-14 15:57:36","data_hora_atualizacao":"2024-05-19 00:21:00","total_comentarios":0,"media_avaliacao":null}