{"id":27837,"bairro":"Charqueadas","cidade":"Caxias do Sul","slug_cidade":"caxias-do-sul","estado":"Rio Grande do Sul","uf":"RS","slug_uf":"rs","faixa_cep_inicial":"95096650","faixa_cep_final":"95110856","slug":"charqueadas","meta_titulo_google":"Charqueadas Cep ruas Charqueadas caxias do sul RS","meta_descricao_google":"Charqueadas caxias do sul cep Charqueadas caxias do sul RS \u2714\ufe0f faixa de cep 95096650 - 95110856 \u2714\ufe0f veja as ruas do bairro Charqueadas","numero_enderecos":135,"data_hora_criacao":"2023-05-19 09:13:29","data_hora_atualizacao":"2024-05-19 00:21:00","total_comentarios":0,"media_avaliacao":null}