{"id":6,"bairro":"Conquista","cidade":"Capixaba","slug_cidade":"capixaba","estado":"Acre","uf":"AC","slug_uf":"ac","faixa_cep_inicial":"69931000","faixa_cep_final":"69931000","slug":"conquista","meta_titulo_google":"Conquista Cep ruas do bairro Conquista capixaba AC","meta_descricao_google":"Conquista capixaba cep Conquista capixaba AC \u2714\ufe0f busca cep 69931000 \u00fanico \u2714\ufe0f veja endere\u00e7os do bairro Conquista capixaba","numero_enderecos":0,"data_hora_criacao":"2023-05-10 02:40:29","data_hora_atualizacao":"2024-05-19 00:22:53","total_comentarios":0,"media_avaliacao":null}