{"id":49965,"bairro":"Cooperativa Habitacional Azulville","cidade":"S\u00e3o Carlos","slug_cidade":"sao-carlos","estado":"S\u00e3o Paulo","uf":"SP","slug_uf":"sp","faixa_cep_inicial":"13571196","faixa_cep_final":"13571198","slug":"cooperativa-habitacional-azulville","meta_titulo_google":"Cooperativa habitacional azulville CEP s\u00e3o carlos SP","meta_descricao_google":"Cooperativa habitacional azulville s\u00e3o carlos cep Cooperativa habitacional azulville s\u00e3o carlos SP cep 13571196 - 13571198","numero_enderecos":2,"data_hora_criacao":"2023-05-22 20:09:32","data_hora_atualizacao":"2024-05-19 00:21:00","total_comentarios":0,"media_avaliacao":null}