{"id":6537,"bairro":"Distrito Agroindustrial de Itumbiara - DIAGRI","cidade":"Itumbiara","slug_cidade":"itumbiara","estado":"Goi\u00e1s","uf":"GO","slug_uf":"go","faixa_cep_inicial":"75536100","faixa_cep_final":"75536140","slug":"distrito-agroindustrial-de-itumbiara-diagri","meta_titulo_google":"Distrito agroindustrial de itumbiara CEP itumbiara GO","meta_descricao_google":"Distrito agroindustrial de itumbiara itumbiara cep Distrito agroindustrial de itumbiara itumbiara GO cep 75536100 - 75536140","numero_enderecos":6,"data_hora_criacao":"2023-05-12 21:26:44","data_hora_atualizacao":"2024-05-19 00:21:00","total_comentarios":0,"media_avaliacao":null}