{"id":12089,"bairro":"Dona Irene","cidade":"Lavras","slug_cidade":"lavras","estado":"Minas Gerais","uf":"MG","slug_uf":"mg","faixa_cep_inicial":"37204210","faixa_cep_final":"37204219","slug":"dona-irene","meta_titulo_google":"Dona irene Cep ruas do bairro Dona irene lavras MG","meta_descricao_google":"Dona irene lavras cep Dona irene lavras MG \u2714\ufe0f faixa de cep 37204210 - 37204219 \u2714\ufe0f consulta as ruas do bairro Dona irene cep","numero_enderecos":7,"data_hora_criacao":"2023-05-14 03:35:27","data_hora_atualizacao":"2024-05-19 00:21:00","total_comentarios":0,"media_avaliacao":null}