{"id":13064,"bairro":"Esplanada","cidade":"Par\u00e1 de Minas","slug_cidade":"para-de-minas","estado":"Minas Gerais","uf":"MG","slug_uf":"mg","faixa_cep_inicial":"35660208","faixa_cep_final":"35660762","slug":"esplanada","meta_titulo_google":"Esplanada Cep ruas do bairro Esplanada par\u00e1 de minas MG","meta_descricao_google":"Esplanada par\u00e1 de minas cep Esplanada par\u00e1 de minas MG \u2714\ufe0f faixa de cep 35660208 - 35660762 \u2714\ufe0f consulta as ruas do bairro Esplanada cep","numero_enderecos":9,"data_hora_criacao":"2023-05-14 08:19:06","data_hora_atualizacao":"2024-05-19 00:21:00","total_comentarios":0,"media_avaliacao":null}