{"id":24240,"bairro":"Foguete","cidade":"Cabo Frio","slug_cidade":"cabo-frio","estado":"Rio de Janeiro","uf":"RJ","slug_uf":"rj","faixa_cep_inicial":"28908150","faixa_cep_final":"28908522","slug":"foguete","meta_titulo_google":"Foguete Cep ruas do bairro Foguete cabo frio RJ","meta_descricao_google":"Foguete cabo frio cep Foguete cabo frio RJ \u2714\ufe0f faixa de cep 28908150 - 28908522 \u2714\ufe0f consulta as ruas do bairro Foguete cep","numero_enderecos":42,"data_hora_criacao":"2023-05-18 06:51:12","data_hora_atualizacao":"2024-05-19 00:21:00","total_comentarios":0,"media_avaliacao":null}