{"id":40851,"bairro":"Gaivotas","cidade":"Ipaussu","slug_cidade":"ipaussu","estado":"S\u00e3o Paulo","uf":"SP","slug_uf":"sp","faixa_cep_inicial":"18950580","faixa_cep_final":"18950598","slug":"gaivotas","meta_titulo_google":"Gaivotas Cep ruas do bairro Gaivotas ipaussu SP","meta_descricao_google":"Gaivotas ipaussu cep Gaivotas ipaussu SP \u2714\ufe0f faixa de cep 18950580 - 18950598 \u2714\ufe0f consulta as ruas do bairro Gaivotas cep","numero_enderecos":10,"data_hora_criacao":"2023-05-21 15:33:53","data_hora_atualizacao":"2024-05-19 00:21:00","total_comentarios":0,"media_avaliacao":null}