{"id":10801,"bairro":"Gr\u00e3-Duquesa","cidade":"Governador Valadares","slug_cidade":"governador-valadares","estado":"Minas Gerais","uf":"MG","slug_uf":"mg","faixa_cep_inicial":"35057010","faixa_cep_final":"35060370","slug":"gra-duquesa","meta_titulo_google":"Gr\u00e3-duquesa Cep ruas Gr\u00e3-duquesa governador MG","meta_descricao_google":"Gr\u00e3-duquesa governador cep Gr\u00e3-duquesa governador MG \u2714\ufe0f faixa de cep 35057010 - 35060370 \u2714\ufe0f veja as ruas do bairro Gr\u00e3-duquesa","numero_enderecos":70,"data_hora_criacao":"2023-05-13 21:27:24","data_hora_atualizacao":"2024-05-19 00:21:00","total_comentarios":0,"media_avaliacao":null}