{"id":40609,"bairro":"Helv\u00e9tia","cidade":"Indaiatuba","slug_cidade":"indaiatuba","estado":"S\u00e3o Paulo","uf":"SP","slug_uf":"sp","faixa_cep_inicial":"13337300","faixa_cep_final":"13337981","slug":"helvetia","meta_titulo_google":"Helv\u00e9tia Cep ruas do bairro Helv\u00e9tia indaiatuba SP","meta_descricao_google":"Helv\u00e9tia indaiatuba cep Helv\u00e9tia indaiatuba SP \u2714\ufe0f faixa de cep 13337300 - 13337981 \u2714\ufe0f consulta as ruas do bairro Helv\u00e9tia cep","numero_enderecos":64,"data_hora_criacao":"2023-05-21 14:52:04","data_hora_atualizacao":"2024-05-19 00:21:00","total_comentarios":0,"media_avaliacao":null}