{"id":24301,"bairro":"Horto Municipal","cidade":"Campos dos Goytacazes","slug_cidade":"campos-dos-goytacazes","estado":"Rio de Janeiro","uf":"RJ","slug_uf":"rj","faixa_cep_inicial":"28015390","faixa_cep_final":"28021730","slug":"horto-municipal","meta_titulo_google":"Horto municipal Cep Horto municipal campos dos RJ","meta_descricao_google":"Horto municipal campos dos cep Horto municipal campos dos RJ \u2714\ufe0f faixa de cep 28015390 - 28021730 \u2714\ufe0f consulte as ruas do bairro","numero_enderecos":14,"data_hora_criacao":"2023-05-18 07:09:01","data_hora_atualizacao":"2024-05-19 00:21:00","total_comentarios":0,"media_avaliacao":null}