{"id":11297,"bairro":"Imbel","cidade":"Itajub\u00e1","slug_cidade":"itajuba","estado":"Minas Gerais","uf":"MG","slug_uf":"mg","faixa_cep_inicial":"37501338","faixa_cep_final":"37501354","slug":"imbel","meta_titulo_google":"Imbel Cep Imbel itajub\u00e1 MG veja as ruas do bairro","meta_descricao_google":"Imbel itajub\u00e1 cep Imbel itajub\u00e1 MG \u2714\ufe0f faixa de cep 37501338 - 37501354 \u2714\ufe0f veja as ruas do bairro Imbel \u2714\ufe0f consulta endere\u00e7o","numero_enderecos":14,"data_hora_criacao":"2023-05-13 23:50:22","data_hora_atualizacao":"2024-05-19 00:21:00","total_comentarios":0,"media_avaliacao":null}