{"id":42086,"bairro":"Jardim Europa","cidade":"Itu","slug_cidade":"itu","estado":"S\u00e3o Paulo","uf":"SP","slug_uf":"sp","faixa_cep_inicial":"13308450","faixa_cep_final":"13308483","slug":"jardim-europa","meta_titulo_google":"Jardim europa Cep ruas Jardim europa itu SP","meta_descricao_google":"Jardim europa itu cep Jardim europa itu SP \u2714\ufe0f faixa de cep 13308450 - 13308483 \u2714\ufe0f veja as ruas do bairro Jardim europa","numero_enderecos":19,"data_hora_criacao":"2023-05-21 19:16:03","data_hora_atualizacao":"2024-05-19 00:21:00","total_comentarios":0,"media_avaliacao":null}