{"id":33998,"bairro":"Jardim Sumar\u00e9","cidade":"Atibaia","slug_cidade":"atibaia","estado":"S\u00e3o Paulo","uf":"SP","slug_uf":"sp","faixa_cep_inicial":"12941500","faixa_cep_final":"12941501","slug":"jardim-sumare","meta_titulo_google":"Jardim sumar\u00e9 Cep ruas Jardim sumar\u00e9 atibaia SP","meta_descricao_google":"Jardim sumar\u00e9 atibaia cep Jardim sumar\u00e9 atibaia SP \u2714\ufe0f faixa de cep 12941500 - 12941501 \u2714\ufe0f veja as ruas do bairro Jardim sumar\u00e9","numero_enderecos":2,"data_hora_criacao":"2023-05-20 10:36:44","data_hora_atualizacao":"2024-05-19 00:21:00","total_comentarios":0,"media_avaliacao":null}