{"id":5743,"bairro":"Jardim Novo Mundo","cidade":"Goi\u00e2nia","slug_cidade":"goiania","estado":"Goi\u00e1s","uf":"GO","slug_uf":"go","faixa_cep_inicial":"74703010","faixa_cep_final":"74715640","slug":"jardim-novo-mundo","meta_titulo_google":"Jardim novo mundo Cep Jardim novo mundo goi\u00e2nia GO","meta_descricao_google":"Jardim novo mundo goi\u00e2nia cep Jardim novo mundo goi\u00e2nia GO \u2714\ufe0f faixa de cep 74703010 - 74715640 \u2714\ufe0f consulte as ruas do bairro","numero_enderecos":218,"data_hora_criacao":"2023-05-12 17:42:09","data_hora_atualizacao":"2024-05-19 00:21:00","total_comentarios":0,"media_avaliacao":null}