{"id":51721,"bairro":"Jardim das Cam\u00e9lias (Zona Sul)","cidade":"S\u00e3o Paulo","slug_cidade":"sao-paulo","estado":"S\u00e3o Paulo","uf":"SP","slug_uf":"sp","faixa_cep_inicial":"04829240","faixa_cep_final":"04829280","slug":"jardim-das-camelias-zona-sul","meta_titulo_google":"Jardim das cam\u00e9lias (zona sul) CEP s\u00e3o paulo SP","meta_descricao_google":"Jardim das cam\u00e9lias (zona sul) s\u00e3o paulo cep Jardim das cam\u00e9lias (zona sul) s\u00e3o paulo SP cep 04829240 - 04829280","numero_enderecos":5,"data_hora_criacao":"2023-05-23 01:34:52","data_hora_atualizacao":"2024-05-19 00:21:00","total_comentarios":0,"media_avaliacao":null}