{"id":39877,"bairro":"Jardim Novo Iporanga","cidade":"Guarulhos","slug_cidade":"guarulhos","estado":"S\u00e3o Paulo","uf":"SP","slug_uf":"sp","faixa_cep_inicial":"07131071","faixa_cep_final":"07131071","slug":"jardim-novo-iporanga","meta_titulo_google":"Jardim novo iporanga Cep do bairro em guarulhos SP","meta_descricao_google":"Jardim novo iporanga guarulhos cep Jardim novo iporanga guarulhos SP \u2714\ufe0f busca cep 07131071 \u00fanico bairro Jardim novo iporanga","numero_enderecos":0,"data_hora_criacao":"2023-05-21 12:46:53","data_hora_atualizacao":"2024-05-19 00:21:00","total_comentarios":0,"media_avaliacao":null}