{"id":16485,"bairro":"Jardim Piratininga","cidade":"Dourados","slug_cidade":"dourados","estado":"Mato Grosso do Sul","uf":"MS","slug_uf":"ms","faixa_cep_inicial":"79831383","faixa_cep_final":"79831430","slug":"jardim-piratininga","meta_titulo_google":"Jardim piratininga Cep do bairro em dourados MS","meta_descricao_google":"Jardim piratininga dourados cep Jardim piratininga dourados MS \u2714\ufe0f faixa de cep 79831383 - 79831430 \u2714\ufe0f ruas do bairro cep","numero_enderecos":16,"data_hora_criacao":"2023-05-15 02:58:21","data_hora_atualizacao":"2024-05-19 00:21:00","total_comentarios":0,"media_avaliacao":null}