{"id":47020,"bairro":"Jardim Itamaraty","cidade":"Piracicaba","slug_cidade":"piracicaba","estado":"S\u00e3o Paulo","uf":"SP","slug_uf":"sp","faixa_cep_inicial":"13425076","faixa_cep_final":"13425076","slug":"jardim-itamaraty","meta_titulo_google":"Jardim itamaraty Cep Jardim itamaraty piracicaba SP","meta_descricao_google":"Jardim itamaraty piracicaba cep Jardim itamaraty piracicaba SP \u2714\ufe0f busca cep 13425076 \u00fanico \u2714\ufe0f veja ruas do bairro Jardim itamaraty","numero_enderecos":0,"data_hora_criacao":"2023-05-22 10:04:34","data_hora_atualizacao":"2024-05-19 00:21:00","total_comentarios":0,"media_avaliacao":null}