{"id":9535,"bairro":"Loteamento Residencial Jardins La vie","cidade":"Caratinga","slug_cidade":"caratinga","estado":"Minas Gerais","uf":"MG","slug_uf":"mg","faixa_cep_inicial":"35304450","faixa_cep_final":"35304474","slug":"loteamento-residencial-jardins-la-vie","meta_titulo_google":"Loteamento residencial jardins la CEP caratinga MG","meta_descricao_google":"Loteamento residencial jardins la caratinga cep Loteamento residencial jardins la caratinga MG cep 35304450 - 35304474","numero_enderecos":9,"data_hora_criacao":"2023-05-13 15:24:22","data_hora_atualizacao":"2024-05-19 00:21:00","total_comentarios":0,"media_avaliacao":null}