{"id":25685,"bairro":"Morada da Colina","cidade":"Resende","slug_cidade":"resende","estado":"Rio de Janeiro","uf":"RJ","slug_uf":"rj","faixa_cep_inicial":"27523000","faixa_cep_final":"27523358","slug":"morada-da-colina","meta_titulo_google":"Morada da colina Cep Morada da colina resende RJ","meta_descricao_google":"Morada da colina resende cep Morada da colina resende RJ \u2714\ufe0f faixa de cep 27523000 - 27523358 \u2714\ufe0f consulte as ruas do bairro","numero_enderecos":40,"data_hora_criacao":"2023-05-18 14:26:44","data_hora_atualizacao":"2024-05-19 00:21:00","total_comentarios":0,"media_avaliacao":null}