{"id":10348,"bairro":"Niter\u00f3i","cidade":"Divin\u00f3polis","slug_cidade":"divinopolis","estado":"Minas Gerais","uf":"MG","slug_uf":"mg","faixa_cep_inicial":"35500214","faixa_cep_final":"35503348","slug":"niteroi","meta_titulo_google":"Niter\u00f3i Cep ruas do bairro Niter\u00f3i divin\u00f3polis MG","meta_descricao_google":"Niter\u00f3i divin\u00f3polis cep Niter\u00f3i divin\u00f3polis MG \u2714\ufe0f faixa de cep 35500214 - 35503348 \u2714\ufe0f consulta as ruas do bairro Niter\u00f3i cep","numero_enderecos":32,"data_hora_criacao":"2023-05-13 19:18:25","data_hora_atualizacao":"2024-05-19 00:21:00","total_comentarios":0,"media_avaliacao":null}