{"id":3765,"bairro":"Nossa Senhora da Concei\u00e7\u00e3o","cidade":"Linhares","slug_cidade":"linhares","estado":"Esp\u00edrito Santo","uf":"ES","slug_uf":"es","faixa_cep_inicial":"29900470","faixa_cep_final":"29901959","slug":"nossa-senhora-da-conceicao","meta_titulo_google":"Nossa senhora da concei\u00e7\u00e3o CEP bairro linhares ES","meta_descricao_google":"Nossa senhora da concei\u00e7\u00e3o linhares cep Nossa senhora da concei\u00e7\u00e3o linhares ES \u2714\ufe0f veja faixa de cep 29900470 - 29901959","numero_enderecos":46,"data_hora_criacao":"2023-05-11 23:04:57","data_hora_atualizacao":"2024-05-19 00:21:00","total_comentarios":0,"media_avaliacao":null}