{"id":35914,"bairro":"Novo Bonfim (Vilarejo)","cidade":"Cabre\u00fava","slug_cidade":"cabreuva","estado":"S\u00e3o Paulo","uf":"SP","slug_uf":"sp","faixa_cep_inicial":"13317770","faixa_cep_final":"13317800","slug":"novo-bonfim-vilarejo","meta_titulo_google":"Novo bonfim (vilarejo) CEP bairro cabre\u00fava SP","meta_descricao_google":"Novo bonfim (vilarejo) cabre\u00fava cep Novo bonfim (vilarejo) cabre\u00fava SP \u2714\ufe0f veja faixa de cep 13317770 - 13317800","numero_enderecos":16,"data_hora_criacao":"2023-05-20 19:09:58","data_hora_atualizacao":"2024-05-19 00:21:00","total_comentarios":0,"media_avaliacao":null}