{"id":22326,"bairro":"Parque Leblon","cidade":"Londrina","slug_cidade":"londrina","estado":"Paran\u00e1","uf":"PR","slug_uf":"pr","faixa_cep_inicial":"86082860","faixa_cep_final":"86084169","slug":"parque-leblon","meta_titulo_google":"Parque leblon Cep ruas Parque leblon londrina PR","meta_descricao_google":"Parque leblon londrina cep Parque leblon londrina PR \u2714\ufe0f faixa de cep 86082860 - 86084169 \u2714\ufe0f veja as ruas do bairro Parque leblon","numero_enderecos":11,"data_hora_criacao":"2023-05-16 23:21:57","data_hora_atualizacao":"2024-05-19 00:21:00","total_comentarios":0,"media_avaliacao":null}