{"id":32986,"bairro":"Parque Industrial II","cidade":"Ara\u00e7atuba","slug_cidade":"aracatuba","estado":"S\u00e3o Paulo","uf":"SP","slug_uf":"sp","faixa_cep_inicial":"16012145","faixa_cep_final":"16012170","slug":"parque-industrial-ii","meta_titulo_google":"Parque industrial ii Cep do bairro em ara\u00e7atuba SP","meta_descricao_google":"Parque industrial ii ara\u00e7atuba cep Parque industrial ii ara\u00e7atuba SP \u2714\ufe0f faixa de cep 16012145 - 16012170 \u2714\ufe0f ruas do bairro cep","numero_enderecos":3,"data_hora_criacao":"2023-05-20 06:14:14","data_hora_atualizacao":"2024-05-19 00:21:00","total_comentarios":0,"media_avaliacao":null}