{"id":54679,"bairro":"Parque Residencial Rinc\u00e3o Novo","cidade":"Taquaritinga","slug_cidade":"taquaritinga","estado":"S\u00e3o Paulo","uf":"SP","slug_uf":"sp","faixa_cep_inicial":"15902150","faixa_cep_final":"15902162","slug":"parque-residencial-rincao-novo","meta_titulo_google":"Parque residencial rinc\u00e3o novo CEP taquaritinga SP","meta_descricao_google":"Parque residencial rinc\u00e3o novo taquaritinga cep Parque residencial rinc\u00e3o novo taquaritinga SP cep 15902150 - 15902162","numero_enderecos":7,"data_hora_criacao":"2023-05-23 10:33:44","data_hora_atualizacao":"2024-05-19 00:21:00","total_comentarios":0,"media_avaliacao":null}