{"id":40254,"bairro":"Parque Residencial Jo\u00e3o Luiz","cidade":"Hortol\u00e2ndia","slug_cidade":"hortolandia","estado":"S\u00e3o Paulo","uf":"SP","slug_uf":"sp","faixa_cep_inicial":"13186490","faixa_cep_final":"13186503","slug":"parque-residencial-joao-luiz","meta_titulo_google":"Parque residencial jo\u00e3o luiz CEP bairro hortol\u00e2ndia SP","meta_descricao_google":"Parque residencial jo\u00e3o luiz hortol\u00e2ndia cep Parque residencial jo\u00e3o luiz hortol\u00e2ndia SP \u2714\ufe0f veja faixa de cep 13186490 - 13186503","numero_enderecos":8,"data_hora_criacao":"2023-05-21 13:52:43","data_hora_atualizacao":"2024-05-19 00:21:00","total_comentarios":0,"media_avaliacao":null}