{"id":7813,"bairro":"Parque Sumar\u00e9","cidade":"Imperatriz","slug_cidade":"imperatriz","estado":"Maranh\u00e3o","uf":"MA","slug_uf":"ma","faixa_cep_inicial":"65906470","faixa_cep_final":"65906482","slug":"parque-sumare","meta_titulo_google":"Parque sumar\u00e9 Cep ruas Parque sumar\u00e9 imperatriz MA","meta_descricao_google":"Parque sumar\u00e9 imperatriz cep Parque sumar\u00e9 imperatriz MA \u2714\ufe0f faixa de cep 65906470 - 65906482 \u2714\ufe0f veja as ruas do bairro Parque sumar\u00e9","numero_enderecos":5,"data_hora_criacao":"2023-05-13 06:53:57","data_hora_atualizacao":"2024-05-19 00:21:00","total_comentarios":0,"media_avaliacao":null}