{"id":25535,"bairro":"Pilotos","cidade":"Quatis","slug_cidade":"quatis","estado":"Rio de Janeiro","uf":"RJ","slug_uf":"rj","faixa_cep_inicial":"27420240","faixa_cep_final":"27420360","slug":"pilotos","meta_titulo_google":"Pilotos Cep ruas do bairro Pilotos quatis RJ","meta_descricao_google":"Pilotos quatis cep Pilotos quatis RJ \u2714\ufe0f faixa de cep 27420240 - 27420360 \u2714\ufe0f consulta as ruas do bairro Pilotos cep","numero_enderecos":8,"data_hora_criacao":"2023-05-18 13:10:16","data_hora_atualizacao":"2024-05-19 00:21:00","total_comentarios":0,"media_avaliacao":null}