{"id":14839,"bairro":"Pindorama","cidade":"Te\u00f3filo Otoni","slug_cidade":"teofilo-otoni","estado":"Minas Gerais","uf":"MG","slug_uf":"mg","faixa_cep_inicial":"39803252","faixa_cep_final":"39803252","slug":"pindorama","meta_titulo_google":"Pindorama Cep ruas do bairro Pindorama te\u00f3filo otoni MG","meta_descricao_google":"Pindorama te\u00f3filo otoni cep Pindorama te\u00f3filo otoni MG \u2714\ufe0f busca cep 39803252 \u00fanico \u2714\ufe0f veja endere\u00e7os do bairro Pindorama te\u00f3filo otoni","numero_enderecos":0,"data_hora_criacao":"2023-05-14 16:57:27","data_hora_atualizacao":"2024-05-19 00:21:00","total_comentarios":0,"media_avaliacao":null}