{"id":23036,"bairro":"Pinheiros","cidade":"Pato Branco","slug_cidade":"pato-branco","estado":"Paran\u00e1","uf":"PR","slug_uf":"pr","faixa_cep_inicial":"85504340","faixa_cep_final":"85504650","slug":"pinheiros","meta_titulo_google":"Pinheiros Cep ruas do bairro Pinheiros pato branco PR","meta_descricao_google":"Pinheiros pato branco cep Pinheiros pato branco PR \u2714\ufe0f faixa de cep 85504340 - 85504650 \u2714\ufe0f consulta as ruas do bairro Pinheiros cep","numero_enderecos":10,"data_hora_criacao":"2023-05-17 05:25:37","data_hora_atualizacao":"2024-05-19 00:21:00","total_comentarios":0,"media_avaliacao":null}