{"id":10226,"bairro":"Ponte Nova","cidade":"Curvelo","slug_cidade":"curvelo","estado":"Minas Gerais","uf":"MG","slug_uf":"mg","faixa_cep_inicial":"35794434","faixa_cep_final":"35794649","slug":"ponte-nova","meta_titulo_google":"Ponte nova Cep ruas do bairro Ponte nova curvelo MG","meta_descricao_google":"Ponte nova curvelo cep Ponte nova curvelo MG \u2714\ufe0f faixa de cep 35794434 - 35794649 \u2714\ufe0f consulta as ruas do bairro Ponte nova cep","numero_enderecos":76,"data_hora_criacao":"2023-05-13 18:42:20","data_hora_atualizacao":"2024-05-19 00:21:00","total_comentarios":0,"media_avaliacao":null}