{"id":6401,"bairro":"Residencial Atl\u00e2ntico Sul","cidade":"Inhumas","slug_cidade":"inhumas","estado":"Goi\u00e1s","uf":"GO","slug_uf":"go","faixa_cep_inicial":"75401230","faixa_cep_final":"75401254","slug":"residencial-atlantico-sul","meta_titulo_google":"Residencial atl\u00e2ntico sul CEP bairro inhumas GO","meta_descricao_google":"Residencial atl\u00e2ntico sul inhumas cep Residencial atl\u00e2ntico sul inhumas GO \u2714\ufe0f veja faixa de cep 75401230 - 75401254","numero_enderecos":9,"data_hora_criacao":"2023-05-12 20:48:18","data_hora_atualizacao":"2024-05-19 00:21:00","total_comentarios":0,"media_avaliacao":null}