{"id":12529,"bairro":"Residencial Terra Jardim","cidade":"Montes Claros","slug_cidade":"montes-claros","estado":"Minas Gerais","uf":"MG","slug_uf":"mg","faixa_cep_inicial":"39406740","faixa_cep_final":"39406769","slug":"residencial-terra-jardim","meta_titulo_google":"Residencial terra jardim CEP bairro montes claros MG","meta_descricao_google":"Residencial terra jardim montes claros cep Residencial terra jardim montes claros MG \u2714\ufe0f veja faixa de cep 39406740 - 39406769","numero_enderecos":20,"data_hora_criacao":"2023-05-14 05:43:48","data_hora_atualizacao":"2024-05-19 00:21:00","total_comentarios":0,"media_avaliacao":null}