{"id":4584,"bairro":"Residencial Alphaville","cidade":"An\u00e1polis","slug_cidade":"anapolis","estado":"Goi\u00e1s","uf":"GO","slug_uf":"go","faixa_cep_inicial":"75106800","faixa_cep_final":"75106880","slug":"residencial-alphaville","meta_titulo_google":"Residencial alphaville CEP bairro an\u00e1polis GO","meta_descricao_google":"Residencial alphaville an\u00e1polis cep Residencial alphaville an\u00e1polis GO \u2714\ufe0f veja faixa de cep 75106800 - 75106880","numero_enderecos":12,"data_hora_criacao":"2023-05-12 02:59:43","data_hora_atualizacao":"2024-05-19 00:21:00","total_comentarios":0,"media_avaliacao":null}