{"id":7146,"bairro":"Residencial dos Buritis","cidade":"Rio Verde","slug_cidade":"rio-verde","estado":"Goi\u00e1s","uf":"GO","slug_uf":"go","faixa_cep_inicial":"75904870","faixa_cep_final":"75904899","slug":"residencial-dos-buritis","meta_titulo_google":"Residencial dos buritis CEP bairro rio verde GO","meta_descricao_google":"Residencial dos buritis rio verde cep Residencial dos buritis rio verde GO \u2714\ufe0f veja faixa de cep 75904870 - 75904899","numero_enderecos":11,"data_hora_criacao":"2023-05-13 03:38:32","data_hora_atualizacao":"2024-05-19 00:21:00","total_comentarios":0,"media_avaliacao":null}