{"id":31843,"bairro":"Santa Rita","cidade":"Rio do Sul","slug_cidade":"rio-do-sul","estado":"Santa Catarina","uf":"SC","slug_uf":"sc","faixa_cep_inicial":"89162290","faixa_cep_final":"89162416","slug":"santa-rita","meta_titulo_google":"Santa rita Cep ruas do bairro Santa rita rio do sul SC","meta_descricao_google":"Santa rita rio do sul cep Santa rita rio do sul SC \u2714\ufe0f faixa de cep 89162290 - 89162416 \u2714\ufe0f consulta as ruas do bairro Santa rita cep","numero_enderecos":28,"data_hora_criacao":"2023-05-20 01:23:43","data_hora_atualizacao":"2024-05-19 00:21:00","total_comentarios":0,"media_avaliacao":null}