{"id":26590,"bairro":"Santa Quit\u00e9ria","cidade":"Coronel Ezequiel","slug_cidade":"coronel-ezequiel","estado":"Rio Grande do Norte","uf":"RN","slug_uf":"rn","faixa_cep_inicial":"59220000","faixa_cep_final":"59220000","slug":"santa-quiteria","meta_titulo_google":"Santa quit\u00e9ria Cep Santa quit\u00e9ria coronel ezequiel RN","meta_descricao_google":"Santa quit\u00e9ria coronel ezequiel cep Santa quit\u00e9ria coronel ezequiel RN \u2714\ufe0f busca cep 59220000 \u00fanico \u2714\ufe0f veja ruas do bairro Santa quit\u00e9ria","numero_enderecos":0,"data_hora_criacao":"2023-05-18 19:37:20","data_hora_atualizacao":"2024-05-19 00:21:00","total_comentarios":0,"media_avaliacao":null}