{"id":22394,"bairro":"S\u00e3o Crist\u00f3v\u00e3o","cidade":"Londrina","slug_cidade":"londrina","estado":"Paran\u00e1","uf":"PR","slug_uf":"pr","faixa_cep_inicial":"86025480","faixa_cep_final":"86025775","slug":"sao-cristovao","meta_titulo_google":"S\u00e3o crist\u00f3v\u00e3o Cep ruas S\u00e3o crist\u00f3v\u00e3o londrina PR","meta_descricao_google":"S\u00e3o crist\u00f3v\u00e3o londrina cep S\u00e3o crist\u00f3v\u00e3o londrina PR \u2714\ufe0f faixa de cep 86025480 - 86025775 \u2714\ufe0f veja as ruas do bairro S\u00e3o crist\u00f3v\u00e3o","numero_enderecos":6,"data_hora_criacao":"2023-05-17 02:21:35","data_hora_atualizacao":"2024-05-19 00:21:00","total_comentarios":0,"media_avaliacao":null}