{"id":31033,"bairro":"S\u00e3o Pedro","cidade":"Brusque","slug_cidade":"brusque","estado":"Santa Catarina","uf":"SC","slug_uf":"sc","faixa_cep_inicial":"88351160","faixa_cep_final":"88355198","slug":"sao-pedro","meta_titulo_google":"S\u00e3o pedro Cep ruas do bairro S\u00e3o pedro brusque SC","meta_descricao_google":"S\u00e3o pedro brusque cep S\u00e3o pedro brusque SC \u2714\ufe0f faixa de cep 88351160 - 88355198 \u2714\ufe0f consulta as ruas do bairro S\u00e3o pedro cep","numero_enderecos":142,"data_hora_criacao":"2023-05-19 21:56:59","data_hora_atualizacao":"2024-05-19 00:21:00","total_comentarios":0,"media_avaliacao":null}