{"id":2386,"bairro":"S\u00e3o Vicente","cidade":"Crate\u00fas","slug_cidade":"crateus","estado":"Cear\u00e1","uf":"CE","slug_uf":"ce","faixa_cep_inicial":"63700150","faixa_cep_final":"63700390","slug":"sao-vicente","meta_titulo_google":"S\u00e3o vicente Cep ruas S\u00e3o vicente crate\u00fas CE","meta_descricao_google":"S\u00e3o vicente crate\u00fas cep S\u00e3o vicente crate\u00fas CE \u2714\ufe0f faixa de cep 63700150 - 63700390 \u2714\ufe0f veja as ruas do bairro S\u00e3o vicente","numero_enderecos":45,"data_hora_criacao":"2023-05-11 16:19:47","data_hora_atualizacao":"2024-05-19 00:22:53","total_comentarios":0,"media_avaliacao":null}