{"id":6911,"bairro":"Setor Machado","cidade":"Mineiros","slug_cidade":"mineiros","estado":"Goi\u00e1s","uf":"GO","slug_uf":"go","faixa_cep_inicial":"75830132","faixa_cep_final":"75830156","slug":"setor-machado","meta_titulo_google":"Setor machado Cep ruas Setor machado mineiros GO","meta_descricao_google":"Setor machado mineiros cep Setor machado mineiros GO \u2714\ufe0f faixa de cep 75830132 - 75830156 \u2714\ufe0f veja as ruas do bairro Setor machado","numero_enderecos":13,"data_hora_criacao":"2023-05-12 23:12:11","data_hora_atualizacao":"2024-05-19 00:21:00","total_comentarios":0,"media_avaliacao":null}