{"id":6959,"bairro":"Setor Central","cidade":"Nova Veneza","slug_cidade":"nova-veneza","estado":"Goi\u00e1s","uf":"GO","slug_uf":"go","faixa_cep_inicial":"75470000","faixa_cep_final":"75470000","slug":"setor-central","meta_titulo_google":"Setor central Cep ruas Setor central nova veneza GO","meta_descricao_google":"Setor central nova veneza cep Setor central nova veneza GO \u2714\ufe0f busca cep 75470000 \u00fanico \u2714\ufe0f ruas do bairro Setor central nova veneza","numero_enderecos":0,"data_hora_criacao":"2023-05-12 23:25:37","data_hora_atualizacao":"2024-05-19 00:21:00","total_comentarios":0,"media_avaliacao":null}