{"id":19085,"bairro":"Tamboril","cidade":"Arcoverde","slug_cidade":"arcoverde","estado":"Pernambuco","uf":"PE","slug_uf":"pe","faixa_cep_inicial":"56512902","faixa_cep_final":"56513130","slug":"tamboril","meta_titulo_google":"Tamboril Cep ruas do bairro Tamboril arcoverde PE","meta_descricao_google":"Tamboril arcoverde cep Tamboril arcoverde PE \u2714\ufe0f faixa de cep 56512902 - 56513130 \u2714\ufe0f consulta as ruas do bairro Tamboril cep","numero_enderecos":14,"data_hora_criacao":"2023-05-16 05:57:39","data_hora_atualizacao":"2024-05-19 00:21:00","total_comentarios":0,"media_avaliacao":null}