{"id":369,"bairro":"Ten\u00f3rio Cavalcante","cidade":"Palmeira dos \u00cdndios","slug_cidade":"palmeira-dos-indios","estado":"Alagoas","uf":"AL","slug_uf":"al","faixa_cep_inicial":"57600800","faixa_cep_final":"57600840","slug":"tenorio-cavalcante","meta_titulo_google":"Ten\u00f3rio cavalcante Cep do bairro em palmeira dos AL","meta_descricao_google":"Ten\u00f3rio cavalcante palmeira dos cep Ten\u00f3rio cavalcante palmeira dos AL \u2714\ufe0f faixa de cep 57600800 - 57600840 \u2714\ufe0f ruas do bairro cep","numero_enderecos":6,"data_hora_criacao":"2023-05-11 02:58:25","data_hora_atualizacao":"2024-05-19 00:22:53","total_comentarios":0,"media_avaliacao":null}