{"id":19035,"bairro":"Timb\u00f3","cidade":"Abreu e Lima","slug_cidade":"abreu-e-lima","estado":"Pernambuco","uf":"PE","slug_uf":"pe","faixa_cep_inicial":"53520005","faixa_cep_final":"53520903","slug":"timbo","meta_titulo_google":"Timb\u00f3 Cep Timb\u00f3 abreu e lima PE veja as ruas do bairro","meta_descricao_google":"Timb\u00f3 abreu e lima cep Timb\u00f3 abreu e lima PE \u2714\ufe0f faixa de cep 53520005 - 53520903 \u2714\ufe0f veja as ruas do bairro Timb\u00f3 \u2714\ufe0f consulta endere\u00e7o","numero_enderecos":55,"data_hora_criacao":"2023-05-16 05:43:31","data_hora_atualizacao":"2024-05-19 00:21:00","total_comentarios":0,"media_avaliacao":null}