{"id":29697,"bairro":"Vera Cruz","cidade":"Gravata\u00ed","slug_cidade":"gravatai","estado":"Rio Grande do Sul","uf":"RS","slug_uf":"rs","faixa_cep_inicial":"94090000","faixa_cep_final":"94090970","slug":"vera-cruz","meta_titulo_google":"Vera cruz Cep ruas do bairro Vera cruz gravata\u00ed RS","meta_descricao_google":"Vera cruz gravata\u00ed cep Vera cruz gravata\u00ed RS \u2714\ufe0f faixa de cep 94090000 - 94090970 \u2714\ufe0f consulta as ruas do bairro Vera cruz cep","numero_enderecos":70,"data_hora_criacao":"2023-05-19 15:30:01","data_hora_atualizacao":"2024-05-19 00:21:00","total_comentarios":0,"media_avaliacao":null}