{"id":25618,"bairro":"Vila Nascente","cidade":"Queimados","slug_cidade":"queimados","estado":"Rio de Janeiro","uf":"RJ","slug_uf":"rj","faixa_cep_inicial":"26310150","faixa_cep_final":"26327230","slug":"vila-nascente","meta_titulo_google":"Vila nascente Cep ruas Vila nascente queimados RJ","meta_descricao_google":"Vila nascente queimados cep Vila nascente queimados RJ \u2714\ufe0f faixa de cep 26310150 - 26327230 \u2714\ufe0f veja as ruas do bairro Vila nascente","numero_enderecos":16,"data_hora_criacao":"2023-05-18 14:03:05","data_hora_atualizacao":"2024-05-19 00:21:00","total_comentarios":0,"media_avaliacao":null}