{"id":13977,"bairro":"Vila Costa Rios","cidade":"Pouso Alegre","slug_cidade":"pouso-alegre","estado":"Minas Gerais","uf":"MG","slug_uf":"mg","faixa_cep_inicial":"37558300","faixa_cep_final":"37558309","slug":"vila-costa-rios","meta_titulo_google":"Vila costa rios Cep Vila costa rios pouso alegre MG","meta_descricao_google":"Vila costa rios pouso alegre cep Vila costa rios pouso alegre MG \u2714\ufe0f faixa de cep 37558300 - 37558309 \u2714\ufe0f consulte as ruas do bairro","numero_enderecos":9,"data_hora_criacao":"2023-05-14 12:47:59","data_hora_atualizacao":"2024-05-19 00:21:00","total_comentarios":0,"media_avaliacao":null}