{"id":47471,"bairro":"Vila Brasiliano de Lima","cidade":"Platina","slug_cidade":"platina","estado":"S\u00e3o Paulo","uf":"SP","slug_uf":"sp","faixa_cep_inicial":"19990080","faixa_cep_final":"19990104","slug":"vila-brasiliano-de-lima","meta_titulo_google":"Vila brasiliano de lima CEP bairro platina SP","meta_descricao_google":"Vila brasiliano de lima platina cep Vila brasiliano de lima platina SP \u2714\ufe0f veja faixa de cep 19990080 - 19990104","numero_enderecos":12,"data_hora_criacao":"2023-05-22 11:27:34","data_hora_atualizacao":"2024-05-19 00:21:00","total_comentarios":0,"media_avaliacao":null}