{"id":21150,"bairro":"Vila Kuster","cidade":"Campo Largo","slug_cidade":"campo-largo","estado":"Paran\u00e1","uf":"PR","slug_uf":"pr","faixa_cep_inicial":"83604550","faixa_cep_final":"83604555","slug":"vila-kuster","meta_titulo_google":"Vila kuster Cep ruas Vila kuster campo largo PR","meta_descricao_google":"Vila kuster campo largo cep Vila kuster campo largo PR \u2714\ufe0f faixa de cep 83604550 - 83604555 \u2714\ufe0f veja as ruas do bairro Vila kuster","numero_enderecos":2,"data_hora_criacao":"2023-05-16 16:32:52","data_hora_atualizacao":"2024-05-19 00:21:00","total_comentarios":0,"media_avaliacao":null}