{"id":49058,"bairro":"Vila Norma","cidade":"Salto","slug_cidade":"salto","estado":"S\u00e3o Paulo","uf":"SP","slug_uf":"sp","faixa_cep_inicial":"13327300","faixa_cep_final":"13327315","slug":"vila-norma","meta_titulo_google":"Vila norma Cep ruas do bairro Vila norma salto SP","meta_descricao_google":"Vila norma salto cep Vila norma salto SP \u2714\ufe0f faixa de cep 13327300 - 13327315 \u2714\ufe0f consulta as ruas do bairro Vila norma cep","numero_enderecos":7,"data_hora_criacao":"2023-05-22 16:11:44","data_hora_atualizacao":"2024-05-19 00:21:00","total_comentarios":0,"media_avaliacao":null}