{"id":55652,"bairro":"Vila Indaia","cidade":"V\u00e1rzea Paulista","slug_cidade":"varzea-paulista","estado":"S\u00e3o Paulo","uf":"SP","slug_uf":"sp","faixa_cep_inicial":"13225450","faixa_cep_final":"13225460","slug":"vila-indaia","meta_titulo_google":"Vila indaia Cep ruas Vila indaia v\u00e1rzea paulista SP","meta_descricao_google":"Vila indaia v\u00e1rzea paulista cep Vila indaia v\u00e1rzea paulista SP \u2714\ufe0f faixa de cep 13225450 - 13225460 \u2714\ufe0f veja as ruas do bairro Vila indaia","numero_enderecos":3,"data_hora_criacao":"2023-05-23 13:39:13","data_hora_atualizacao":"2024-05-19 00:21:00","total_comentarios":0,"media_avaliacao":null}