{"id":24289,"bairro":"Vivamar (Tamoios)","cidade":"Cabo Frio","slug_cidade":"cabo-frio","estado":"Rio de Janeiro","uf":"RJ","slug_uf":"rj","faixa_cep_inicial":"28929330","faixa_cep_final":"28929362","slug":"vivamar-tamoios","meta_titulo_google":"Vivamar (tamoios) Cep Vivamar (tamoios) cabo frio RJ","meta_descricao_google":"Vivamar (tamoios) cabo frio cep Vivamar (tamoios) cabo frio RJ \u2714\ufe0f faixa de cep 28929330 - 28929362 \u2714\ufe0f consulte as ruas do bairro","numero_enderecos":17,"data_hora_criacao":"2023-05-18 07:05:21","data_hora_atualizacao":"2024-05-19 00:21:00","total_comentarios":0,"media_avaliacao":null}